{
  "unitId": "U3",
  "unitName": "Unit 3 Learning better",
  "words": [
    {
      "text": "find",
      "meaning": "",
      "round": 0,
      "nextReview": null,
      "wrongCount": 0,
      "history": []
    },
    {
      "text": "see",
      "meaning": "",
      "round": 0,
      "nextReview": null,
      "wrongCount": 0,
      "history": []
    },
    {
      "text": "smell",
      "meaning": "",
      "round": 0,
      "nextReview": null,
      "wrongCount": 0,
      "history": []
    },
    {
      "text": "taste",
      "meaning": "",
      "round": 0,
      "nextReview": null,
      "wrongCount": 0,
      "history": []
    },
    {
      "text": "hear",
      "meaning": "",
      "round": 0,
      "nextReview": null,
      "wrongCount": 0,
      "history": []
    },
    {
      "text": "touch",
      "meaning": "",
      "round": 0,
      "nextReview": null,
      "wrongCount": 0,
      "history": []
    },
    {
      "text": "learn",
      "meaning": "",
      "round": 0,
      "nextReview": null,
      "wrongCount": 0,
      "history": []
    },
    {
      "text": "nose",
      "meaning": "",
      "round": 0,
      "nextReview": null,
      "wrongCount": 0,
      "history": []
    },
    {
      "text": "tongue",
      "meaning": "",
      "round": 0,
      "nextReview": null,
      "wrongCount": 0,
      "history": []
    },
    {
      "text": "class",
      "meaning": "",
      "round": 0,
      "nextReview": null,
      "wrongCount": 0,
      "history": []
    }
  ]
}